setup.py
LianJiaSpider.egg-info/PKG-INFO
LianJiaSpider.egg-info/SOURCES.txt
LianJiaSpider.egg-info/dependency_links.txt
LianJiaSpider.egg-info/requires.txt
LianJiaSpider.egg-info/top_level.txt
Lianjia/__init__.py
Lianjia/lianjia.py