Metadata-Version: 1.0
Name: LianJiaSpider
Version: 1.2.0
Summary: An self made api for lianjia
Home-page: https://github.com/xjkj123/Lianjia/
Author: Mrx
Author-email: xjkj123@icloud.com
License: GNU Licence
Keywords: pip,LianJiaSpider,API,链家
Platform: any
